django_enum/__init__.py
django_enum/base.py
django_enum_simple_choices-1.0.1.dist-info/LICENSE
django_enum_simple_choices-1.0.1.dist-info/METADATA
django_enum_simple_choices-1.0.1.dist-info/WHEEL
django_enum_simple_choices-1.0.1.dist-info/top_level.txt
django_enum_simple_choices-1.0.1.dist-info/RECORD
